bnv/__init__.py
bnv-0.1.1a1.dist-info/WHEEL
bnv-0.1.1a1.dist-info/METADATA
bnv-0.1.1a1.dist-info/RECORD
